labrecorder_controller/__init__.py
labrecorder_controller/main.py
labrecorder_controller-0.0.2.dist-info/METADATA
labrecorder_controller-0.0.2.dist-info/WHEEL
labrecorder_controller-0.0.2.dist-info/top_level.txt
labrecorder_controller-0.0.2.dist-info/RECORD
