Metadata-Version: 2.1
Name: labrecorder-controller
Version: 0.0.2
Summary: python library for controll lab recorder.
Home-page: https://github.com/simonkojima/labrecorder-controller
Author: Simon Kojima
Author-email: simon.kojima@outlook.com
Project-URL: Bug Tracker, https://github.com/simonkojima/labrecorder-controller/issues
Classifier: Programming Language :: Python :: 3
Classifier: License :: OSI Approved :: MIT License
Classifier: Operating System :: OS Independent
Requires-Python: >=3.6
